design.sv
// Code your design here
module counter4 (
    input  logic       clk,
    input  logic       rst_n,   // Reset assíncrono ativo em 0
    input  logic       en,      // Enable síncrono
    output logic [3:0] count
);

always_ff @(posedge clk or negedge rst_n) begin
    if (!rst_n)
        count <= 4'd0;
    else if (en)
        count <= count + 4'd1;
    else
        count <= count;
end

endmodule

testbench.sv
// Code your testbench here
// or browse Examples
`timescale 1ns/1ps

module tb_counter4;

logic clk;
logic rst_n;
logic en;
logic [3:0] count;
  
initial begin
    $dumpfile("dump.vcd");
    $dumpvars(0, tb_counter4);
end

// Instanciação do DUT
counter4 DUT (
    .clk(clk),
    .rst_n(rst_n),
    .en(en),
    .count(count)
);

  
// Geração do clock (10 ns de período)


initial begin
    clk = 0;
    forever #5 clk = ~clk;
end


// Monitor


initial begin
    $display("Tempo\tclk\trst_n\ten\tcount");
    $monitor("%0t\t%b\t%b\t%b\t%0d",
             $time, clk, rst_n, en, count);
end


// Testes


integer i;
logic [3:0] expected;

initial begin


    // Inicialização


    rst_n = 1;
    en    = 0;
    expected = 0;


    // Teste 1 - Reset Assíncrono


    #2;
    rst_n = 0;

    #2;

    if (count !== 4'd0)
        $error("ERRO: Reset assíncrono falhou.");
    else
        $display("Teste Reset Assíncrono: PASSOU");

    #6;
    rst_n = 1;


    // Teste 2 - Enable = 0


    repeat (5) begin
        @(posedge clk);

        if (count !== 4'd0)
            $error("ERRO: Contador alterou com enable=0");
    end

    $display("Teste Enable=0: PASSOU");


    // Teste 3 - Contagem de 0 até 15


    en = 1;
    expected = 0;

    for(i=0; i<16; i++) begin

        @(posedge clk);

        expected = expected + 1;

        if(count !== expected)
            $error("ERRO: Esperado=%0d Obtido=%0d",
                    expected, count);

    end

    $display("Teste Contagem Crescente: PASSOU");


    // Teste 4 - Overflow


    @(posedge clk);

    if(count !== 4'd1)
        $error("ERRO Overflow");
    else
        $display("Teste Overflow: PASSOU");


    // Teste 5 - Desabilita durante contagem


    en = 0;

    repeat(4) begin

        @(posedge clk);

        if(count !== 4'd1)
            $error("ERRO: contador incrementou com enable=0");

    end

    $display("Teste Desabilitação: PASSOU");


    // Teste 6 - Reabilita


    en = 1;

    @(posedge clk);

    if(count !== 4'd2)
        $error("ERRO: contador não retomou corretamente");
    else
        $display("Teste Reabilitação: PASSOU");

  
    // Teste 7 - Reset durante contagem


    @(posedge clk);

    rst_n = 0;

    #1;

    if(count !== 4'd0)
        $error("ERRO: Reset durante contagem falhou");
    else
        $display("Teste Reset Durante Contagem: PASSOU");

    #9;
    rst_n = 1;


    // Teste Final


    en = 1;

    repeat(5)
        @(posedge clk);


    $display("Todos os testes foram executados.");


    #20;
    $finish;

end

endmodule

dump.vcd
$date
	Wed Jul 22 14:51:43 2026
$end
$version
	Icarus Verilog
$end
$timescale
	1ps
$end
$scope module tb_counter4 $end
$var wire 4 ! count [3:0] $end
$var reg 1 " clk $end
$var reg 1 # en $end
$var reg 4 $ expected [3:0] $end
$var reg 1 % rst_n $end
$var integer 32 & i [31:0] $end
$scope module DUT $end
$var wire 1 " clk $end
$var wire 1 # en $end
$var wire 1 % rst_n $end
$var reg 4 ' count [3:0] $end
$upscope $end
$upscope $end
$enddefinitions $end
$comment Show the parameter values. $end
$dumpall
$end
#0
$dumpvars
bx '
bx &
1%
b0 $
0#
0"
bx !
$end
#2000
b0 !
b0 '
0%
#5000
1"
#10000
0"
1%
#15000
1"
#20000
0"
#25000
1"
#30000
0"
#35000
1"
#40000
0"
#45000
1"
#50000
0"
#55000
b1 !
b1 '
b0 &
1#
1"
#60000
0"
#65000
b10 !
b10 '
b1 &
b1 $
1"
#70000
0"
#75000
b11 !
b11 '
b10 &
b10 $
1"
#80000
0"
#85000
b100 !
b100 '
b11 &
b11 $
1"
#90000
0"
#95000
b101 !
b101 '
b100 &
b100 $
1"
#100000
0"
#105000
b110 !
b110 '
b101 &
b101 $
1"
#110000
0"
#115000
b111 !
b111 '
b110 &
b110 $
1"
#120000
0"
#125000
b1000 !
b1000 '
b111 &
b111 $
1"
#130000
0"
#135000
b1001 !
b1001 '
b1000 &
b1000 $
1"
#140000
0"
#145000
b1010 !
b1010 '
b1001 &
b1001 $
1"
#150000
0"
#155000
b1011 !
b1011 '
b1010 &
b1010 $
1"
#160000
0"
#165000
b1100 !
b1100 '
b1011 &
b1011 $
1"
#170000
0"
#175000
b1101 !
b1101 '
b1100 &
b1100 $
1"
#180000
0"
#185000
b1110 !
b1110 '
b1101 &
b1101 $
1"
#190000
0"
#195000
b1111 !
b1111 '
b1110 &
b1110 $
1"
#200000
0"
#205000
b0 !
b0 '
b1111 &
b1111 $
1"
#210000
0"
#215000
b1 !
b1 '
b10000 &
b0 $
1"
#220000
0"
#225000
0#
1"
#230000
0"
#235000
1"
#240000
0"
#245000
1"
#250000
0"
#255000
1"
#260000
0"
#265000
b10 !
b10 '
1#
1"
#270000
0"
#275000
b11 !
b11 '
1"
#280000
0"
#285000
b0 !
b0 '
0%
1"
#290000
0"
#295000
b1 !
b1 '
1"
1%
#300000
0"
#305000
b10 !
b10 '
1"
#310000
0"
#315000
b11 !
b11 '
1"
#320000
0"
#325000
b100 !
b100 '
1"
#330000
0"
#335000
b101 !
b101 '
1"
#340000
0"
#345000
b110 !
b110 '
1"
#350000
0"
#355000
b111 !
b111 '
1"
